{
  "Surging": {
    "Ip": "${Surging_Server_IP}|0.0.0.0",
    "WatchInterval": 30,
    "Port": "${Surging_Server_Port}|98",
    "MappingIp": "${Mapping_ip}",
    "MappingPort": "${Mapping_Port}",
    "Token": "true",
    "WanIp": "${WanIp}",
    "Libuv": true,
    "SoBacklog": 100,
    "MaxConcurrentRequests": 20,
    "DisconnTimeInterval": 30,
    "ExecutionTimeoutInMilliseconds": 1000,
    "Protocol": "${Protocol}|None", //Http、Tcp、None
    "RootPath": "${RootPath}|./userapp",
    "WebRootPath": "${WebRootPath}|./wwwroot",
    "IsModulePerLifetimeScope": false,
    "ReloadOnChange": false,
    "Ports": {
      "HttpPort": "${HttpPort}|8080",
      "WSPort": "${WSPort}|96",
      "MQTTPort": "${MQTTPort}|97"
    },
    "RequestCacheEnabled": false,
    "Packages": [
      {
        "TypeName": "EnginePartModule",
        "Using": "${UseEngineParts}|ServiceProxyModule;DotNettyModule;NLogModule;MessagePackModule;ConsulModule;WSProtocolModule;MqttProtocolModule;EventBusRabbitMQModule;CachingModule;KestrelHttpModule;DnsProtocolModule;SwaggerModule;ApiGeteWayModule;SkywalkingModule;"
      },
      {
        "TypeName": "KestrelHttpModule",
        "Using": "${UseKestrelHttpParts}|StageModule,SwaggerModule"
      }
    ]
  }, //如果引用多个同类型的组件，需要配置Packages，如果是自定义按需引用，无需配置Packages
  "DbSetting": {
    "DbType": "${DbType}|MySql", //MySql SqlServer, Oracle, Postgres
    "ConnectionString": "${ConnectionString}|Server=mysql;Database=surging_demo;Uid=root;Port=3306;Pwd=Surging!P4ss"
  },
  "Automapper": {
    "Assemblies": "Surging.Hero.*.Application;Surging.Hero.Common;Surging.*.Common;"
  },
  "Stage": {
    "EnableHttps": true, // 不设置ports，默认httpsPort:443
    "CertificateFileName": "${CertificateFileName}|",
    "CertificateLocation": "${CertificateLocation}|pfxs",
    "CertificatePassword": "${CertificatePassword}|",
    "IsCamelCaseResolver": "${IsCamelCaseResolver}|true",
    "Protocols": "Http1AndHttp2",
    "ApiGetWay": {
      "AccessTokenExpireTimeSpan": "30",
      "AuthorizationRoutePath": "api/user/authentication",
      "AuthorizationServiceKey": "User",
      "TokenEndpointPath": "api/oauth2/token",
      "CacheMode": "MemoryCache" //MemoryCache or  gateway.Redis save token
    },
    "AccessPolicy": {
      "Origins": [ "http://127.0.0.1:1927", "http://localhost:927" ],
      "AllowAnyHeader": true,
      "AllowAnyMethod": true
    },
    "AccessSetting": [
      {
        "BlackList": "${blacklist}|127.0.0.1",
        "Enable": false
      },
      {
        "WhiteList": "${whitelist}",
        "BlackList": "${blacklist}",
        "RoutePath": "api/user/exists",
        "Enable": true
      }
    ],
    "HttpsPort": "${StageHttpsPorts}|449,446",
    "HttpPorts": "${StageHttpPorts}|285,282,283"
  },
  "Dns": {
    "RootDnsAddress": "192.168.1.1",
    "QueryTimeout": 1000
  },
  "Swagger": {
    "Info": {
      "Version": "${SwaggerVersion}|V1", // "127.0.0.1:8500",
      "Title": "${SwaggerTitle}|jingshonline",
      "Description": "${SwaggerDes}|jingshonline",
      "Contact": {
        "Name": "API Support",
        "Url": "",
        "Email": "",
        "License": {
          "Name": "",
          "Url": ""
        }
      }
    },
    "Options": {
      "IgnoreFullyQualified": false,
      "MapRoutePaths": [
        {
          "SourceRoutePath": "api/user/authentication",
          "TargetRoutePath": "api/oauth2/token"
        }
      ]
      // "IngressName": "Notice"
    }
  },
  "Logging": {
    "Debug": {
      "LogLevel": {
        "Default": "Information"
      }
    },
    "Console": {
      "IncludeScopes": true,
      "LogLevel": {
        "Default": "${LogLevel}|Debug"
      }
    },
    "LogLevel": {
      "Default": "${LogLevel}|Debug"
    }
  }
}
